iboot/__init__.py
iboot/command.py
iboot/iboot.py
iboot/onboarding.py
iboot/pack_model.py
iBoot-1.2.9.dist-info/METADATA
iBoot-1.2.9.dist-info/WHEEL
iBoot-1.2.9.dist-info/entry_points.txt
iBoot-1.2.9.dist-info/top_level.txt
iBoot-1.2.9.dist-info/RECORD
