Metadata-Version: 2.1
Name: iBoot
Version: 1.2.9
Summary: iBoot —— AI模型服务化引擎
Home-page: https://git.openi.org.cn/OpenI/cubeai_iboot
Author: cubeai
Author-email: cubeai@163.com
License: Apache License 2.0
Keywords: iBoot micro-service web RESTful API cloud-native AI模型 服务化 云原生 微服务
Platform: UNKNOWN
Classifier: Development Status :: 4 - Beta
Classifier: Intended Audience :: Developers
Classifier: Intended Audience :: Science/Research
Classifier: Programming Language :: Python :: 3
Classifier: Programming Language :: Python :: 3.5
Classifier: Programming Language :: Python :: 3.6
Classifier: Programming Language :: Python :: 3.7
Classifier: Programming Language :: Python :: 3.8
Classifier: Programming Language :: Python :: 3.9
Classifier: License :: OSI Approved :: Apache Software License
Requires-Python: >=3.5
Requires-Dist: cython (==0.29.21)
Requires-Dist: requests (==2.24.0)
Requires-Dist: tornado (==6.0.4)
Requires-Dist: pyyaml (==5.3.1)
